tests/__init__.py
tests/test_callbacks.py
tests/test_tensorboard.py
tests/test_trainer.py
torchflow/__init__.py
torchflow/callbacks.py
torchflow/trainer.py
torchflow/tuner.py
torchflow/utils.py
torchflow_core-0.1.0.dist-info/licenses/LICENSE
torchflow_core-0.1.0.dist-info/METADATA
torchflow_core-0.1.0.dist-info/WHEEL
torchflow_core-0.1.0.dist-info/top_level.txt
torchflow_core-0.1.0.dist-info/RECORD
