Metadata-Version: 2.4
Name: torchflow-core
Version: 0.1.0
Summary: Lightweight PyTorch training utilities (Trainer, Callbacks, Tuner)
Home-page: https://github.com/mobadara/torchflow
Author: Muyiwa J. Obadara
Author-email: "Muyiwa J. Obadara" <muyiwa.j.obadara@gmail.com>
License: MIT License
Project-URL: Homepage, https://github.com/mobadara/torchflow
License-File: LICENSE
Dynamic: license-file
